odoo/__init__.py
odoo/addons/__init__.py
odoo/addons/event_phone/__init__.py
odoo/addons/event_phone/__manifest__.py
odoo/addons/event_phone/i18n/es.po
odoo/addons/event_phone/i18n/event_phone.pot
odoo/addons/event_phone/i18n/tr.po
odoo/addons/event_phone/models/__init__.py
odoo/addons/event_phone/models/event_registration.py
odoo/addons/event_phone/security/ir.model.access.csv
odoo/addons/event_phone/views/hr_registration.xml
odoo12_addon_event_phone-12.0.1.0.0.dist-info/METADATA
odoo12_addon_event_phone-12.0.1.0.0.dist-info/RECORD
odoo12_addon_event_phone-12.0.1.0.0.dist-info/WHEEL
odoo12_addon_event_phone-12.0.1.0.0.dist-info/top_level.txt
